primepackage/__init__.py
primepackage-2.0.dist-info/LICENSE
primepackage-2.0.dist-info/WHEEL
primepackage-2.0.dist-info/METADATA
primepackage-2.0.dist-info/RECORD
